rvc_infer/__init__.py
rvc_infer/infer.py
rvc_infer/pipeline.py
rvc_infer/libslor/__init__.py
rvc_infer/libslor/attentions.py
rvc_infer/libslor/audio.py
rvc_infer/libslor/commons.py
rvc_infer/libslor/fcpe.py
rvc_infer/libslor/models.py
rvc_infer/libslor/modules.py
rvc_infer/libslor/rmvpe.py
rvc_infer/libslor/transforms.py
rvc_infer-2024.6.7.1.dist-info/LICENSE
rvc_infer-2024.6.7.1.dist-info/METADATA
rvc_infer-2024.6.7.1.dist-info/WHEEL
rvc_infer-2024.6.7.1.dist-info/top_level.txt
rvc_infer-2024.6.7.1.dist-info/RECORD
