Metadata-Version: 2.1
Name: rvc_infer
Version: 2024.6.7.1
Summary: Python wrapper for inference with rvc
Home-page: https://github.com/blane187gt/rvc_infer
Author: blane187gt
License: MIT
Requires-Python: >=3.10
License-File: LICENSE
Requires-Dist: deemix
Requires-Dist: fairseq
Requires-Dist: faiss-cpu
Requires-Dist: ffmpeg-python>=0.2.0
Requires-Dist: resampy==0.4.2
Requires-Dist: gradio
Requires-Dist: fairseq==0.12.2
Requires-Dist: librosa
Requires-Dist: numpy
Requires-Dist: audio-separator[gpu]
Requires-Dist: scipy
Requires-Dist: yt-dlp
Requires-Dist: onnxruntime-gpu
Requires-Dist: praat-parselmouth==0.4.2
Requires-Dist: pedalboard
Requires-Dist: pydub==0.25.1
Requires-Dist: pyworld==0.3.4
Requires-Dist: requests
Requires-Dist: soundfile
Requires-Dist: torch
Requires-Dist: torchcrepe==0.0.20
Requires-Dist: tqdm
Requires-Dist: torchfcpe
Requires-Dist: einops
Requires-Dist: local-attention
Requires-Dist: ffmpeg
Requires-Dist: pyworld
Requires-Dist: sox
Requires-Dist: av
Requires-Dist: gdown
Requires-Dist: mega.py
Provides-Extra: all
Requires-Dist: numba==0.56.4; extra == "all"
Requires-Dist: edge-tts; extra == "all"
